{
	"id": 10,
	"path": [
		{"latitude":21.955007,"longitude":-102.251354},
		{"latitude":21.955290,"longitude":-102.251580},
		{"latitude":21.955494,"longitude":-102.251880},
		{"latitude":21.955599,"longitude":-102.252191},
		{"latitude":21.955639,"longitude":-102.252470},
		{"latitude":21.955649,"longitude":-102.252894},
		{"latitude":21.955698,"longitude":-102.253345},
		{"latitude":21.955838,"longitude":-102.253672},
		{"latitude":21.956012,"longitude":-102.253929},
		{"latitude":21.956310,"longitude":-102.254139},
		{"latitude":21.956559,"longitude":-102.254321},
		{"latitude":21.957002,"longitude":-102.254868},
		{"latitude":21.957554,"longitude":-102.255539},
		{"latitude":21.957823,"longitude":-102.255726},
		{"latitude":21.958106,"longitude":-102.255855},
		{"latitude":21.958405,"longitude":-102.256011},
		{"latitude":21.958778,"longitude":-102.256376},
		{"latitude":21.958907,"longitude":-102.256606},
		{"latitude":21.958982,"longitude":-102.256848},
		{"latitude":21.959072,"longitude":-102.257266},
		{"latitude":21.959296,"longitude":-102.257604},
		{"latitude":21.959380,"longitude":-102.257727},
		{"latitude":21.959131,"longitude":-102.257996},
		{"latitude":21.958858,"longitude":-102.258328},
		{"latitude":21.958569,"longitude":-102.258838},
		{"latitude":21.958450,"longitude":-102.259101},
		{"latitude":21.958221,"longitude":-102.259707},
		{"latitude":21.958116,"longitude":-102.260131},
		{"latitude":21.957917,"longitude":-102.260774},
		{"latitude":21.957828,"longitude":-102.261123},
		{"latitude":21.957748,"longitude":-102.261563},
		{"latitude":21.957679,"longitude":-102.262073},
		{"latitude":21.957634,"longitude":-102.262330},
		{"latitude":21.957609,"longitude":-102.262577},
		{"latitude":21.957609,"longitude":-102.262888},
		{"latitude":21.957634,"longitude":-102.263188},
		{"latitude":21.957664,"longitude":-102.263505},
		{"latitude":21.957783,"longitude":-102.263913},
		{"latitude":21.957907,"longitude":-102.264159},
		{"latitude":21.958047,"longitude":-102.264379},
		{"latitude":21.958166,"longitude":-102.264572},
		{"latitude":21.958301,"longitude":-102.264787},
		{"latitude":21.958480,"longitude":-102.265023},
		{"latitude":21.958738,"longitude":-102.265382},
		{"latitude":21.958868,"longitude":-102.265613},
		{"latitude":21.959176,"longitude":-102.266611},
		{"latitude":21.959375,"longitude":-102.267233},
		{"latitude":21.959435,"longitude":-102.267357},
		{"latitude":21.959684,"longitude":-102.268081},
		{"latitude":21.960022,"longitude":-102.269057},
		{"latitude":21.960365,"longitude":-102.270092},
		{"latitude":21.960420,"longitude":-102.270328},
		{"latitude":21.960594,"longitude":-102.270859},
		{"latitude":21.959833,"longitude":-102.271160},
		{"latitude":21.959713,"longitude":-102.271374},
		{"latitude":21.959335,"longitude":-102.271492},
		{"latitude":21.958400,"longitude":-102.271857},
		{"latitude":21.957664,"longitude":-102.272211},
		{"latitude":21.957256,"longitude":-102.272437},
		{"latitude":21.956967,"longitude":-102.272576},
		{"latitude":21.957027,"longitude":-102.273134},
		{"latitude":21.957196,"longitude":-102.274067},
		{"latitude":21.957375,"longitude":-102.275151},
		{"latitude":21.957584,"longitude":-102.276438},
		{"latitude":21.958738,"longitude":-102.276213},
		{"latitude":21.959564,"longitude":-102.276042},
		{"latitude":21.960320,"longitude":-102.275913},
		{"latitude":21.959893,"longitude":-102.273552},
		{"latitude":21.960052,"longitude":-102.273477},
		{"latitude":21.960261,"longitude":-102.274486},
		{"latitude":21.960450,"longitude":-102.275752},
		{"latitude":21.960390,"longitude":-102.276192},
		{"latitude":21.960619,"longitude":-102.277329},
		{"latitude":21.960977,"longitude":-102.277844},
		{"latitude":21.961286,"longitude":-102.279925},
		{"latitude":21.961505,"longitude":-102.281363},
		{"latitude":21.961723,"longitude":-102.282844},
		{"latitude":21.962042,"longitude":-102.284850},
		{"latitude":21.962261,"longitude":-102.286320},
		{"latitude":21.962709,"longitude":-102.289227},
		{"latitude":21.962878,"longitude":-102.290053},
		{"latitude":21.962251,"longitude":-102.290075},
		{"latitude":21.961514,"longitude":-102.290118},
		{"latitude":21.960997,"longitude":-102.290118},
		{"latitude":21.960529,"longitude":-102.290128},
		{"latitude":21.959694,"longitude":-102.290139},
		{"latitude":21.958509,"longitude":-102.290236},
		{"latitude":21.957315,"longitude":-102.290279},
		{"latitude":21.955942,"longitude":-102.290332},
		{"latitude":21.954957,"longitude":-102.290397},
		{"latitude":21.953942,"longitude":-102.290418},
		{"latitude":21.953345,"longitude":-102.290483},
		{"latitude":21.951653,"longitude":-102.290536},
		{"latitude":21.950111,"longitude":-102.290601},
		{"latitude":21.948449,"longitude":-102.290643},
		{"latitude":21.946817,"longitude":-102.290708},
		{"latitude":21.945842,"longitude":-102.290751},
		{"latitude":21.944757,"longitude":-102.290826},
		{"latitude":21.943225,"longitude":-102.290912},
		{"latitude":21.940548,"longitude":-102.290998},
		{"latitude":21.938945,"longitude":-102.291083},
		{"latitude":21.937910,"longitude":-102.291126},
		{"latitude":21.935721,"longitude":-102.291266},
		{"latitude":21.935253,"longitude":-102.291309},
		{"latitude":21.934785,"longitude":-102.291352},
		{"latitude":21.933930,"longitude":-102.291362},
		{"latitude":21.933770,"longitude":-102.291276},
		{"latitude":21.933143,"longitude":-102.291319},
		{"latitude":21.931342,"longitude":-102.291427},
		{"latitude":21.930178,"longitude":-102.291470},
		{"latitude":21.929212,"longitude":-102.291480},
		{"latitude":21.927809,"longitude":-102.291555},
		{"latitude":21.927620,"longitude":-102.291598},
		{"latitude":21.927281,"longitude":-102.291609},
		{"latitude":21.925898,"longitude":-102.291652},
		{"latitude":21.924833,"longitude":-102.291695},
		{"latitude":21.923788,"longitude":-102.291770},
		{"latitude":21.922394,"longitude":-102.291802},
		{"latitude":21.921001,"longitude":-102.291802},
		{"latitude":21.918941,"longitude":-102.291877},
		{"latitude":21.918154,"longitude":-102.291963},
		{"latitude":21.917468,"longitude":-102.292049},
		{"latitude":21.917259,"longitude":-102.292049},
		{"latitude":21.915995,"longitude":-102.292124},
		{"latitude":21.914661,"longitude":-102.292167},
		{"latitude":21.913855,"longitude":-102.292188},
		{"latitude":21.913118,"longitude":-102.292199},
		{"latitude":21.912809,"longitude":-102.292231},
		{"latitude":21.912640,"longitude":-102.292188},
		{"latitude":21.911874,"longitude":-102.292242},
		{"latitude":21.910998,"longitude":-102.292274},
		{"latitude":21.910291,"longitude":-102.292317},
		{"latitude":21.908917,"longitude":-102.292382},
		{"latitude":21.908051,"longitude":-102.292424},
		{"latitude":21.907225,"longitude":-102.292467},
		{"latitude":21.906369,"longitude":-102.292521},
		{"latitude":21.903721,"longitude":-102.292607},
		{"latitude":21.901900,"longitude":-102.292703},
		{"latitude":21.900874,"longitude":-102.292682},
		{"latitude":21.900267,"longitude":-102.292703},
		{"latitude":21.899929,"longitude":-102.292757},
		{"latitude":21.899222,"longitude":-102.292789},
		{"latitude":21.897669,"longitude":-102.292843},
		{"latitude":21.896275,"longitude":-102.292918},
		{"latitude":21.894384,"longitude":-102.292993},
		{"latitude":21.893946,"longitude":-102.292972},
		{"latitude":21.893518,"longitude":-102.293143},
		{"latitude":21.892612,"longitude":-102.293766},
		{"latitude":21.892403,"longitude":-102.293900},
		{"latitude":21.892134,"longitude":-102.294248},
		{"latitude":21.891850,"longitude":-102.294549},
		{"latitude":21.891547,"longitude":-102.294914},
		{"latitude":21.891248,"longitude":-102.294951},
		{"latitude":21.891079,"longitude":-102.294699},
		{"latitude":21.890676,"longitude":-102.294307},
		{"latitude":21.890442,"longitude":-102.294039},
		{"latitude":21.890193,"longitude":-102.293760},
		{"latitude":21.889839,"longitude":-102.293342},
		{"latitude":21.889590,"longitude":-102.293594},
		{"latitude":21.889093,"longitude":-102.294071},
		{"latitude":21.888630,"longitude":-102.294559},
		{"latitude":21.888112,"longitude":-102.295074},
		{"latitude":21.887515,"longitude":-102.295643},
		{"latitude":21.887266,"longitude":-102.295761},
		{"latitude":21.887136,"longitude":-102.295933},
		{"latitude":21.886947,"longitude":-102.296083},
		{"latitude":21.886718,"longitude":-102.296351},
		{"latitude":21.886340,"longitude":-102.296244},
		{"latitude":21.885399,"longitude":-102.295901},
		{"latitude":21.884872,"longitude":-102.295691},
		{"latitude":21.884140,"longitude":-102.295364},
		{"latitude":21.883712,"longitude":-102.295310},
		{"latitude":21.883040,"longitude":-102.295091},
		{"latitude":21.882198,"longitude":-102.294814},
		{"latitude":21.881474,"longitude":-102.294578},
		{"latitude":21.880822,"longitude":-102.294409},
		{"latitude":21.880175,"longitude":-102.294197},
		{"latitude":21.879493,"longitude":-102.293980},
		{"latitude":21.879055,"longitude":-102.293803},
		{"latitude":21.878507,"longitude":-102.293607},
		{"latitude":21.877676,"longitude":-102.293331},
		{"latitude":21.876205,"longitude":-102.292854},
		{"latitude":21.874701,"longitude":-102.292382},
		{"latitude":21.873591,"longitude":-102.292092},
		{"latitude":21.873298,"longitude":-102.292049},
		{"latitude":21.872949,"longitude":-102.291958},
		{"latitude":21.872765,"longitude":-102.291915},
		{"latitude":21.872501,"longitude":-102.291813},
		{"latitude":21.872357,"longitude":-102.292478},
		{"latitude":21.872242,"longitude":-102.293057},
		{"latitude":21.872118,"longitude":-102.293433},
		{"latitude":21.871774,"longitude":-102.294179},
		{"latitude":21.871510,"longitude":-102.294538},
		{"latitude":21.871152,"longitude":-102.294897},
		{"latitude":21.870983,"longitude":-102.294935},
		{"latitude":21.870913,"longitude":-102.295042},
		{"latitude":21.870774,"longitude":-102.295160},
		{"latitude":21.870241,"longitude":-102.295096},
		{"latitude":21.869484,"longitude":-102.294983},
		{"latitude":21.868250,"longitude":-102.294774},
		{"latitude":21.867602,"longitude":-102.294651},
		{"latitude":21.866542,"longitude":-102.294474},
		{"latitude":21.865900,"longitude":-102.294340},
		{"latitude":21.865671,"longitude":-102.294345},
		{"latitude":21.865566,"longitude":-102.294436},
		{"latitude":21.865571,"longitude":-102.294661},
		{"latitude":21.865636,"longitude":-102.295074},
		{"latitude":21.865745,"longitude":-102.295884},
		{"latitude":21.865950,"longitude":-102.296872},
		{"latitude":21.866014,"longitude":-102.297311},
		{"latitude":21.866009,"longitude":-102.297494},
		{"latitude":21.866139,"longitude":-102.298261},
		{"latitude":21.866348,"longitude":-102.299452},
		{"latitude":21.866567,"longitude":-102.300627},
		{"latitude":21.866776,"longitude":-102.301759},
		{"latitude":21.866960,"longitude":-102.302831},
		{"latitude":21.866985,"longitude":-102.302998},
		{"latitude":21.866144,"longitude":-102.303175},
		{"latitude":21.865238,"longitude":-102.303368},
		{"latitude":21.864506,"longitude":-102.303523},
		{"latitude":21.864222,"longitude":-102.303609},
		{"latitude":21.863719,"longitude":-102.303679},
		{"latitude":21.863311,"longitude":-102.303663},
		{"latitude":21.862977,"longitude":-102.303615},
		{"latitude":21.862599,"longitude":-102.303475},
		{"latitude":21.862171,"longitude":-102.303196},
		{"latitude":21.861787,"longitude":-102.302874},
		{"latitude":21.861419,"longitude":-102.302295},
		{"latitude":21.861115,"longitude":-102.301785},
		{"latitude":21.860787,"longitude":-102.301147},
		{"latitude":21.860563,"longitude":-102.301045},
		{"latitude":21.860379,"longitude":-102.301067},
		{"latitude":21.860244,"longitude":-102.301147},
		{"latitude":21.859955,"longitude":-102.301592},
		{"latitude":21.859731,"longitude":-102.302354},
		{"latitude":21.859443,"longitude":-102.303427},
		{"latitude":21.859149,"longitude":-102.304360},
		{"latitude":21.858820,"longitude":-102.305481},
		{"latitude":21.858616,"longitude":-102.306184},
		{"latitude":21.858566,"longitude":-102.306431},
		{"latitude":21.858661,"longitude":-102.307252},
		{"latitude":21.858810,"longitude":-102.308722},
		{"latitude":21.858890,"longitude":-102.309735},
		{"latitude":21.859044,"longitude":-102.311307},
		{"latitude":21.859139,"longitude":-102.312364},
		{"latitude":21.859248,"longitude":-102.313920},
		{"latitude":21.857974,"longitude":-102.314762},
		{"latitude":21.857103,"longitude":-102.315320},
		{"latitude":21.856152,"longitude":-102.315990},
		{"latitude":21.855544,"longitude":-102.316430},
		{"latitude":21.854867,"longitude":-102.316843},
		{"latitude":21.854160,"longitude":-102.317358},
		{"latitude":21.853792,"longitude":-102.317433},
		{"latitude":21.853483,"longitude":-102.317659},
		{"latitude":21.853811,"longitude":-102.318624},
		{"latitude":21.854499,"longitude":-102.320459},
		{"latitude":21.855524,"longitude":-102.323248},
		{"latitude":21.853811,"longitude":-102.323956},
		{"latitude":21.852866,"longitude":-102.321446},
		{"latitude":21.852397,"longitude":-102.320201},
		{"latitude":21.851681,"longitude":-102.318292},
		{"latitude":21.851312,"longitude":-102.318431},
		{"latitude":21.850436,"longitude":-102.318774},
		{"latitude":21.849330,"longitude":-102.319214},
		{"latitude":21.849081,"longitude":-102.319311},
		{"latitude":21.848877,"longitude":-102.318683},
		{"latitude":21.848793,"longitude":-102.318179},
		{"latitude":21.848608,"longitude":-102.317149},
		{"latitude":21.848598,"longitude":-102.316993},
		{"latitude":21.848922,"longitude":-102.316843},
		{"latitude":21.849286,"longitude":-102.316645},
		{"latitude":21.849460,"longitude":-102.317069}
	],
	"stroke": {
		"weight": 3
		},
	"editable": false,
	"draggable": false,
	"geodesic": true,
	"visible": true,
	"icons": [
		{
		"offset": "25px",
		"repeat": "50px"
		}
	]
}