{
	"id": 54,
	"path": [
		{"latitude":21.851217,"longitude":-102.297923},
		{"latitude":21.850261,"longitude":-102.297515},
		{"latitude":21.850112,"longitude":-102.297955},
		{"latitude":21.849928,"longitude":-102.298588},
		{"latitude":21.849873,"longitude":-102.298851},
		{"latitude":21.849764,"longitude":-102.299720},
		{"latitude":21.849694,"longitude":-102.300578},
		{"latitude":21.849684,"longitude":-102.301034},
		{"latitude":21.849729,"longitude":-102.301211},
		{"latitude":21.849858,"longitude":-102.301764},
		{"latitude":21.850037,"longitude":-102.302611},
		{"latitude":21.850172,"longitude":-102.303212},
		{"latitude":21.850242,"longitude":-102.303582},
		{"latitude":21.850336,"longitude":-102.304065},
		{"latitude":21.850456,"longitude":-102.304510},
		{"latitude":21.850590,"longitude":-102.305052},
		{"latitude":21.850690,"longitude":-102.305519},
		{"latitude":21.850779,"longitude":-102.305959},
		{"latitude":21.850884,"longitude":-102.306409},
		{"latitude":21.850993,"longitude":-102.306855},
		{"latitude":21.851083,"longitude":-102.307332},
		{"latitude":21.851237,"longitude":-102.308319},
		{"latitude":21.851297,"longitude":-102.308727},
		{"latitude":21.851287,"longitude":-102.308893},
		{"latitude":21.851397,"longitude":-102.309456},
		{"latitude":21.851695,"longitude":-102.310368},
		{"latitude":21.852024,"longitude":-102.311361},
		{"latitude":21.852293,"longitude":-102.312278},
		{"latitude":21.852462,"longitude":-102.312799},
		{"latitude":21.852636,"longitude":-102.313297},
		{"latitude":21.852915,"longitude":-102.314145},
		{"latitude":21.853085,"longitude":-102.314676},
		{"latitude":21.852492,"longitude":-102.314982},
		{"latitude":21.851636,"longitude":-102.315406},
		{"latitude":21.850934,"longitude":-102.315770},
		{"latitude":21.850197,"longitude":-102.316141},
		{"latitude":21.849370,"longitude":-102.316591},
		{"latitude":21.848932,"longitude":-102.316822},
		{"latitude":21.848683,"longitude":-102.316940},
		{"latitude":21.848783,"longitude":-102.317567},
		{"latitude":21.848897,"longitude":-102.318286},
		{"latitude":21.848957,"longitude":-102.318791},
		{"latitude":21.849037,"longitude":-102.319220},
		{"latitude":21.849515,"longitude":-102.319027},
		{"latitude":21.849774,"longitude":-102.319627},
		{"latitude":21.850097,"longitude":-102.320609},
		{"latitude":21.850441,"longitude":-102.321618},
		{"latitude":21.850779,"longitude":-102.322454},
		{"latitude":21.850944,"longitude":-102.322932},
		{"latitude":21.851128,"longitude":-102.323404},
		{"latitude":21.851287,"longitude":-102.323871},
		{"latitude":21.851471,"longitude":-102.324364},
		{"latitude":21.851666,"longitude":-102.324831},
		{"latitude":21.851850,"longitude":-102.325308},
		{"latitude":21.852024,"longitude":-102.325748},
		{"latitude":21.852183,"longitude":-102.326210},
		{"latitude":21.852363,"longitude":-102.326666},
		{"latitude":21.852537,"longitude":-102.327159},
		{"latitude":21.853090,"longitude":-102.326928},
		{"latitude":21.854623,"longitude":-102.326290},
		{"latitude":21.854284,"longitude":-102.325351},
		{"latitude":21.853782,"longitude":-102.323946},
		{"latitude":21.853413,"longitude":-102.322986},
		{"latitude":21.853080,"longitude":-102.322063},
		{"latitude":21.852736,"longitude":-102.321135},
		{"latitude":21.852402,"longitude":-102.320201},
		{"latitude":21.852218,"longitude":-102.319745},
		{"latitude":21.852049,"longitude":-102.319247},
		{"latitude":21.851900,"longitude":-102.318791},
		{"latitude":21.851636,"longitude":-102.318131},
		{"latitude":21.852004,"longitude":-102.317997},
		{"latitude":21.852831,"longitude":-102.317664},
		{"latitude":21.853657,"longitude":-102.317310},
		{"latitude":21.854444,"longitude":-102.316897},
		{"latitude":21.855146,"longitude":-102.316452},
		{"latitude":21.855942,"longitude":-102.315910},
		{"latitude":21.856664,"longitude":-102.315373},
		{"latitude":21.857406,"longitude":-102.314896},
		{"latitude":21.858168,"longitude":-102.314445},
		{"latitude":21.858965,"longitude":-102.314005},
		{"latitude":21.859761,"longitude":-102.313598},
		{"latitude":21.860438,"longitude":-102.313185},
		{"latitude":21.861315,"longitude":-102.312697},
		{"latitude":21.862086,"longitude":-102.312241},
		{"latitude":21.862833,"longitude":-102.311769},
		{"latitude":21.863615,"longitude":-102.311339},
		{"latitude":21.864396,"longitude":-102.310862},
		{"latitude":21.865168,"longitude":-102.310406},
		{"latitude":21.865955,"longitude":-102.309977},
		{"latitude":21.866711,"longitude":-102.309510},
		{"latitude":21.867488,"longitude":-102.309049},
		{"latitude":21.867981,"longitude":-102.308732},
		{"latitude":21.868095,"longitude":-102.309183},
		{"latitude":21.868200,"longitude":-102.309440},
		{"latitude":21.868329,"longitude":-102.309671},
		{"latitude":21.868504,"longitude":-102.309875},
		{"latitude":21.868747,"longitude":-102.310073},
		{"latitude":21.868971,"longitude":-102.310186},
		{"latitude":21.869350,"longitude":-102.310315},
		{"latitude":21.870241,"longitude":-102.310663},
		{"latitude":21.871655,"longitude":-102.311060},
		{"latitude":21.873636,"longitude":-102.311651},
		{"latitude":21.874263,"longitude":-102.311822},
		{"latitude":21.874194,"longitude":-102.312241},
		{"latitude":21.873865,"longitude":-102.313120},
		{"latitude":21.873367,"longitude":-102.314408},
		{"latitude":21.872760,"longitude":-102.315964},
		{"latitude":21.872023,"longitude":-102.317734},
		{"latitude":21.871734,"longitude":-102.318528},
		{"latitude":21.872471,"longitude":-102.318463},
		{"latitude":21.873437,"longitude":-102.318420},
		{"latitude":21.874164,"longitude":-102.318356},
		{"latitude":21.875876,"longitude":-102.318206},
		{"latitude":21.876952,"longitude":-102.318104},
		{"latitude":21.878156,"longitude":-102.318002},
		{"latitude":21.878490,"longitude":-102.317991},
		{"latitude":21.879032,"longitude":-102.317900},
		{"latitude":21.879769,"longitude":-102.317873},
		{"latitude":21.880750,"longitude":-102.317787},
		{"latitude":21.881740,"longitude":-102.317702},
		{"latitude":21.882726,"longitude":-102.317632},
		{"latitude":21.883682,"longitude":-102.317573},
		{"latitude":21.884185,"longitude":-102.317535},
		{"latitude":21.884747,"longitude":-102.317449},
		{"latitude":21.885718,"longitude":-102.317289},
		{"latitude":21.886410,"longitude":-102.317154},
		{"latitude":21.887843,"longitude":-102.316854},
		{"latitude":21.888142,"longitude":-102.316822},
		{"latitude":21.890093,"longitude":-102.316865},
		{"latitude":21.891517,"longitude":-102.316875},
		{"latitude":21.892562,"longitude":-102.316886},
		{"latitude":21.892587,"longitude":-102.317117},
		{"latitude":21.892567,"longitude":-102.317879},
		{"latitude":21.892537,"longitude":-102.319161},
		{"latitude":21.892532,"longitude":-102.320185},
		{"latitude":21.892517,"longitude":-102.321226},
		{"latitude":21.893309,"longitude":-102.321247},
		{"latitude":21.894379,"longitude":-102.321247},
		{"latitude":21.895155,"longitude":-102.321269},
		{"latitude":21.895907,"longitude":-102.321280},
		{"latitude":21.896644,"longitude":-102.321290},
		{"latitude":21.897395,"longitude":-102.321301},
		{"latitude":21.897754,"longitude":-102.321306},
		{"latitude":21.898142,"longitude":-102.321328},
		{"latitude":21.898495,"longitude":-102.321349},
		{"latitude":21.898500,"longitude":-102.321210},
		{"latitude":21.898431,"longitude":-102.320985},
		{"latitude":21.898266,"longitude":-102.320464},
		{"latitude":21.898052,"longitude":-102.319885},
		{"latitude":21.897798,"longitude":-102.319316},
		{"latitude":21.897694,"longitude":-102.318984},
		{"latitude":21.897674,"longitude":-102.318769},
		{"latitude":21.897694,"longitude":-102.318592},
		{"latitude":21.897749,"longitude":-102.318388},
		{"latitude":21.897838,"longitude":-102.318104},
		{"latitude":21.897948,"longitude":-102.317938},
		{"latitude":21.898416,"longitude":-102.317192},
		{"latitude":21.898515,"longitude":-102.316999},
		{"latitude":21.898669,"longitude":-102.316993},
		{"latitude":21.899396,"longitude":-102.316961},
		{"latitude":21.899804,"longitude":-102.316913},
		{"latitude":21.900372,"longitude":-102.316816},
		{"latitude":21.900735,"longitude":-102.316725},
		{"latitude":21.901103,"longitude":-102.316586},
		{"latitude":21.901317,"longitude":-102.316521},
		{"latitude":21.901840,"longitude":-102.316403},
		{"latitude":21.902422,"longitude":-102.316280},
		{"latitude":21.902611,"longitude":-102.316226},
		{"latitude":21.902731,"longitude":-102.316173},
		{"latitude":21.903249,"longitude":-102.316124},
		{"latitude":21.903487,"longitude":-102.316130},
		{"latitude":21.903711,"longitude":-102.316130},
		{"latitude":21.903940,"longitude":-102.316162},
		{"latitude":21.904244,"longitude":-102.316205},
		{"latitude":21.905205,"longitude":-102.316414},
		{"latitude":21.906190,"longitude":-102.316623},
		{"latitude":21.907161,"longitude":-102.316816},
		{"latitude":21.908081,"longitude":-102.316999},
		{"latitude":21.909067,"longitude":-102.317224},
		{"latitude":21.909460,"longitude":-102.317294},
		{"latitude":21.910057,"longitude":-102.317401},
		{"latitude":21.910789,"longitude":-102.317589},
		{"latitude":21.910983,"longitude":-102.317648},
		{"latitude":21.911943,"longitude":-102.317986},
		{"latitude":21.912864,"longitude":-102.318340},
		{"latitude":21.913790,"longitude":-102.318715},
		{"latitude":21.914083,"longitude":-102.318812},
		{"latitude":21.914367,"longitude":-102.318860},
		{"latitude":21.914701,"longitude":-102.318866},
		{"latitude":21.915039,"longitude":-102.318774},
		{"latitude":21.915278,"longitude":-102.318640},
		{"latitude":21.915616,"longitude":-102.318388},
		{"latitude":21.915985,"longitude":-102.317911},
		{"latitude":21.916114,"longitude":-102.317482},
		{"latitude":21.916184,"longitude":-102.316779},
		{"latitude":21.916134,"longitude":-102.316398},
		{"latitude":21.916184,"longitude":-102.315733},
		{"latitude":21.916214,"longitude":-102.315293},
		{"latitude":21.916278,"longitude":-102.314306},
		{"latitude":21.916278,"longitude":-102.313930},
		{"latitude":21.916293,"longitude":-102.313544},
		{"latitude":21.916268,"longitude":-102.313276},
		{"latitude":21.916238,"longitude":-102.312675},
		{"latitude":21.916204,"longitude":-102.311967},
		{"latitude":21.916233,"longitude":-102.311624},
		{"latitude":21.916253,"longitude":-102.311490},
		{"latitude":21.916218,"longitude":-102.311093},
		{"latitude":21.916149,"longitude":-102.309870},
		{"latitude":21.916114,"longitude":-102.309253},
		{"latitude":21.916089,"longitude":-102.308587},
		{"latitude":21.916014,"longitude":-102.307890},
		{"latitude":21.916004,"longitude":-102.307359},
		{"latitude":21.915960,"longitude":-102.306587},
		{"latitude":21.915965,"longitude":-102.306114},
		{"latitude":21.915885,"longitude":-102.304870},
		{"latitude":21.915825,"longitude":-102.303883},
		{"latitude":21.915820,"longitude":-102.303636},
		{"latitude":21.915820,"longitude":-102.302912},
		{"latitude":21.915805,"longitude":-102.302375},
		{"latitude":21.915731,"longitude":-102.301104},
		{"latitude":21.915676,"longitude":-102.299854},
		{"latitude":21.915641,"longitude":-102.298604},
		{"latitude":21.915631,"longitude":-102.297360},
		{"latitude":21.915596,"longitude":-102.296914},
		{"latitude":21.915547,"longitude":-102.296104},
		{"latitude":21.915497,"longitude":-102.295219},
		{"latitude":21.915472,"longitude":-102.294828},
		{"latitude":21.915422,"longitude":-102.293621},
		{"latitude":21.915397,"longitude":-102.292365},
		{"latitude":21.915372,"longitude":-102.291631},
		{"latitude":21.915333,"longitude":-102.291164},
		{"latitude":21.915278,"longitude":-102.290568},
		{"latitude":21.915193,"longitude":-102.290338},
		{"latitude":21.915148,"longitude":-102.289453},
		{"latitude":21.915094,"longitude":-102.288197},
		{"latitude":21.915049,"longitude":-102.287296},
		{"latitude":21.915029,"longitude":-102.286701},
		{"latitude":21.915014,"longitude":-102.286465},
		{"latitude":21.915417,"longitude":-102.286448},
		{"latitude":21.915815,"longitude":-102.286357},
		{"latitude":21.916627,"longitude":-102.286196},
		{"latitude":21.917463,"longitude":-102.286030},
		{"latitude":21.918314,"longitude":-102.285880},
		{"latitude":21.919160,"longitude":-102.285746},
		{"latitude":21.919682,"longitude":-102.285665},
		{"latitude":21.920026,"longitude":-102.285601},
		{"latitude":21.920827,"longitude":-102.285419},
		{"latitude":21.921678,"longitude":-102.285225},
		{"latitude":21.922519,"longitude":-102.285032},
		{"latitude":21.923345,"longitude":-102.284850},
		{"latitude":21.924196,"longitude":-102.284667},
		{"latitude":21.926296,"longitude":-102.284163},
		{"latitude":21.929620,"longitude":-102.283412},
		{"latitude":21.931660,"longitude":-102.282940},
		{"latitude":21.931999,"longitude":-102.282878},
		{"latitude":21.932337,"longitude":-102.282760},
		{"latitude":21.932720,"longitude":-102.282637},
		{"latitude":21.933171,"longitude":-102.282436},
		{"latitude":21.933915,"longitude":-102.282103},
		{"latitude":21.934776,"longitude":-102.281733},
		{"latitude":21.935196,"longitude":-102.281553},
		{"latitude":21.935512,"longitude":-102.281452},
		{"latitude":21.935937,"longitude":-102.281374},
		{"latitude":21.936338,"longitude":-102.281315},
		{"latitude":21.936776,"longitude":-102.281248},
		{"latitude":21.937189,"longitude":-102.281135},
		{"latitude":21.937592,"longitude":-102.281014},
		{"latitude":21.937983,"longitude":-102.280816},
		{"latitude":21.938356,"longitude":-102.280582},
		{"latitude":21.939102,"longitude":-102.280127},
		{"latitude":21.939490,"longitude":-102.279893},
		{"latitude":21.939858,"longitude":-102.279705},
		{"latitude":21.940237,"longitude":-102.279494},
		{"latitude":21.940607,"longitude":-102.279282},
		{"latitude":21.940998,"longitude":-102.279070},
		{"latitude":21.941170,"longitude":-102.278970},
		{"latitude":21.941224,"longitude":-102.278815},
		{"latitude":21.941204,"longitude":-102.278697},
		{"latitude":21.941150,"longitude":-102.278504},
		{"latitude":21.940682,"longitude":-102.278048},
		{"latitude":21.939562,"longitude":-102.276986},
		{"latitude":21.938488,"longitude":-102.275945},
		{"latitude":21.937403,"longitude":-102.274915},
		{"latitude":21.936676,"longitude":-102.274271},
		{"latitude":21.935661,"longitude":-102.273477},
		{"latitude":21.934696,"longitude":-102.272737},
		{"latitude":21.933293,"longitude":-102.271600},
		{"latitude":21.932720,"longitude":-102.271144},
		{"latitude":21.931536,"longitude":-102.270205},
		{"latitude":21.930367,"longitude":-102.269277},
		{"latitude":21.929610,"longitude":-102.268682},
		{"latitude":21.928605,"longitude":-102.267866},
		{"latitude":21.928008,"longitude":-102.267340},
		{"latitude":21.927381,"longitude":-102.266504},
		{"latitude":21.926863,"longitude":-102.266010},
		{"latitude":21.926515,"longitude":-102.265538},
		{"latitude":21.925350,"longitude":-102.264229},
		{"latitude":21.924733,"longitude":-102.263553},
		{"latitude":21.924505,"longitude":-102.263317},
		{"latitude":21.923768,"longitude":-102.262899},
		{"latitude":21.923589,"longitude":-102.262866},
		{"latitude":21.922653,"longitude":-102.262362},
		{"latitude":21.922016,"longitude":-102.262105},
		{"latitude":21.921797,"longitude":-102.262030},
		{"latitude":21.921160,"longitude":-102.261912},
		{"latitude":21.920603,"longitude":-102.261837},
		{"latitude":21.920553,"longitude":-102.261472},
		{"latitude":21.921111,"longitude":-102.261528},
		{"latitude":21.921626,"longitude":-102.261625},
		{"latitude":21.922133,"longitude":-102.261796},
		{"latitude":21.922628,"longitude":-102.261992},
		{"latitude":21.922778,"longitude":-102.262089},
		{"latitude":21.922882,"longitude":-102.262180},
		{"latitude":21.923106,"longitude":-102.262303},
		{"latitude":21.923838,"longitude":-102.262716},
		{"latitude":21.924266,"longitude":-102.262952},
		{"latitude":21.924445,"longitude":-102.262963},
		{"latitude":21.924768,"longitude":-102.263178},
		{"latitude":21.925156,"longitude":-102.263521},
		{"latitude":21.925321,"longitude":-102.263677},
		{"latitude":21.925540,"longitude":-102.263902},
		{"latitude":21.925868,"longitude":-102.263623},
		{"latitude":21.926610,"longitude":-102.263162},
		{"latitude":21.927383,"longitude":-102.262689},
		{"latitude":21.927908,"longitude":-102.262354},
		{"latitude":21.928369,"longitude":-102.262035},
		{"latitude":21.929031,"longitude":-102.261619},
		{"latitude":21.929399,"longitude":-102.261378},
		{"latitude":21.930312,"longitude":-102.260796},
		{"latitude":21.931073,"longitude":-102.260345},
		{"latitude":21.931427,"longitude":-102.260104},
		{"latitude":21.931860,"longitude":-102.260941},
		{"latitude":21.932944,"longitude":-102.262909},
		{"latitude":21.933278,"longitude":-102.263499},
		{"latitude":21.933671,"longitude":-102.264181},
		{"latitude":21.934099,"longitude":-102.263934},
		{"latitude":21.935064,"longitude":-102.263339},
		{"latitude":21.935905,"longitude":-102.262802},
		{"latitude":21.936905,"longitude":-102.262158},
		{"latitude":21.937612,"longitude":-102.261708},
		{"latitude":21.937905,"longitude":-102.261536},
		{"latitude":21.938045,"longitude":-102.261437},
		{"latitude":21.938147,"longitude":-102.261364},
		{"latitude":21.938291,"longitude":-102.261225},
		{"latitude":21.938386,"longitude":-102.261120},
		{"latitude":21.938537,"longitude":-102.260906},
		{"latitude":21.938624,"longitude":-102.260836},
		{"latitude":21.939023,"longitude":-102.261161},
		{"latitude":21.939276,"longitude":-102.261378},
		{"latitude":21.939035,"longitude":-102.261708},
		{"latitude":21.938771,"longitude":-102.262110},
		{"latitude":21.938483,"longitude":-102.262518}
	],
	"stroke": {
		"color": "#6060FB",
		"weight": 3
		},
	"editable": false,
	"draggable": false,
	"geodesic": true,
	"visible": true,
	"icons": [
		{
		"icon": {
		"path": "maps.SymbolPath.BACKWARD_OPEN_ARROW"
		},
		"offset": "25px",
		"repeat": "50px"
		}
	]
}